{"1": {"becameSuitTime": 1482453189.421, "savedBy": null, "track": "l", "numFloors": 2, "difficulty": 3, "state": "suit", "block": 1}, "2": {"becameSuitTime": 1482452613.258, "savedBy": null, "track": "l", "numFloors": 4, "difficulty": 4, "state": "suit", "block": 2}, "3": {"becameSuitTime": 1482452794.641, "savedBy": null, "track": "l", "numFloors": 3, "difficulty": 2, "state": "suit", "block": 3}, "4": {"becameSuitTime": 1482453158.516, "savedBy": null, "track": "l", "numFloors": 2, "difficulty": 2, "state": "suit", "block": 4}, "8": {"becameSuitTime": 1482453059.381, "savedBy": null, "track": "c", "numFloors": 4, "difficulty": 4, "state": "suit", "block": 8}, "9": {"becameSuitTime": 1482453161.185, "savedBy": null, "track": "l", "numFloors": 3, "difficulty": 4, "state": "suit", "block": 9}, "11": {"becameSuitTime": 1482452897.284, "savedBy": null, "track": "l", "numFloors": 2, "difficulty": 4, "state": "suit", "block": 11}, "15": {"becameSuitTime": 1482452998.938, "savedBy": null, "track": "l", "numFloors": 2, "difficulty": 3, "state": "suit", "block": 15}, "17": {"becameSuitTime": 1482452417.132, "savedBy": null, "track": "l", "numFloors": 2, "difficulty": 4, "state": "suit", "block": 17}, "20": {"becameSuitTime": 1482453753.419, "savedBy": null, "track": "l", "numFloors": 3, "difficulty": 3, "state": "suit", "block": 20}, "21": {"becameSuitTime": 1482452544.275, "savedBy": null, "track": "s", "numFloors": 3, "difficulty": 4, "state": "suit", "block": 21}, "25": {"becameSuitTime": 1482453347.728, "savedBy": null, "track": "l", "numFloors": 3, "difficulty": 2, "state": "suit", "block": 25}, "26": {"becameSuitTime": 1482453736.767, "savedBy": null, "track": "l", "numFloors": 4, "difficulty": 4, "state": "suit", "block": 26}}