{"35": {"becameSuitTime": 1482426560.541, "savedBy": null, "track": "s", "numFloors": 2, "difficulty": 4, "state": "suit", "block": 35}, "4": {"becameSuitTime": 1482382448.698, "savedBy": null, "track": "s", "numFloors": 2, "difficulty": 4, "state": "suit", "block": 4}, "5": {"becameSuitTime": 1482382340.652, "savedBy": null, "track": "s", "numFloors": 3, "difficulty": 5, "state": "suit", "block": 5}, "15": {"becameSuitTime": 1482382262.103, "savedBy": null, "track": "s", "numFloors": 4, "difficulty": 4, "state": "suit", "block": 15}, "19": {"becameSuitTime": 1482404491.78, "savedBy": null, "track": "s", "numFloors": 3, "difficulty": 3, "state": "suit", "block": 19}, "26": {"becameSuitTime": 1482405719.576, "savedBy": null, "track": "c", "numFloors": 4, "difficulty": 6, "state": "suit", "block": 26}, "27": {"becameSuitTime": 1482382340.465, "savedBy": null, "track": "s", "numFloors": 4, "difficulty": 5, "state": "suit", "block": 27}, "28": {"becameSuitTime": 1482382472.405, "savedBy": null, "track": "s", "numFloors": 2, "difficulty": 2, "state": "suit", "block": 28}, "30": {"becameSuitTime": 1482382391.517, "savedBy": null, "track": "s", "numFloors": 1, "difficulty": 2, "state": "suit", "block": 30}}