{"33": {"becameSuitTime": 1482194340.686, "savedBy": null, "track": "g", "numFloors": 1, "difficulty": 2, "state": "suit", "block": 33}, "34": {"becameSuitTime": 1482194354.591, "savedBy": null, "track": "m", "numFloors": 2, "difficulty": 2, "state": "suit", "block": 34}, "4": {"becameSuitTime": 1482194294.081, "savedBy": null, "track": "c", "numFloors": 3, "difficulty": 5, "state": "suit", "block": 4}, "5": {"becameSuitTime": 1482194472.858, "savedBy": null, "track": "s", "numFloors": 2, "difficulty": 4, "state": "suit", "block": 5}, "6": {"becameSuitTime": 1482194361.87, "savedBy": null, "track": "c", "numFloors": 1, "difficulty": 2, "state": "suit", "block": 6}, "8": {"becameSuitTime": 1482194141.833, "savedBy": null, "track": "l", "numFloors": 1, "difficulty": 2, "state": "suit", "block": 8}, "9": {"becameSuitTime": 1482194511.332, "savedBy": null, "track": "l", "numFloors": 3, "difficulty": 3, "state": "suit", "block": 9}, "15": {"becameSuitTime": 1482194134.033, "savedBy": null, "track": "g", "numFloors": 4, "difficulty": 4, "state": "suit", "block": 15}, "23": {"becameSuitTime": 1482194095.007, "savedBy": null, "track": "g", "numFloors": 4, "difficulty": 5, "state": "suit", "block": 23}}