{"2": {"becameSuitTime": 1482193954.37, "savedBy": null, "track": "s", "numFloors": 5, "difficulty": 6, "state": "suit", "block": 2}, "35": {"becameSuitTime": 1482194527.31, "savedBy": null, "track": "s", "numFloors": 4, "difficulty": 6, "state": "suit", "block": 35}, "5": {"becameSuitTime": 1482194407.856, "savedBy": null, "track": "g", "numFloors": 5, "difficulty": 6, "state": "suit", "block": 5}, "6": {"becameSuitTime": 1482194087.587, "savedBy": null, "track": "m", "numFloors": 4, "difficulty": 6, "state": "suit", "block": 6}, "17": {"becameSuitTime": 1482194128.943, "savedBy": null, "track": "s", "numFloors": 5, "difficulty": 6, "state": "suit", "block": 17}, "21": {"becameSuitTime": 1482194277.685, "savedBy": null, "track": "s", "numFloors": 5, "difficulty": 7, "state": "suit", "block": 21}, "24": {"becameSuitTime": 1482194438.087, "savedBy": null, "track": "c", "numFloors": 2, "difficulty": 4, "state": "suit", "block": 24}, "26": {"becameSuitTime": 1482194531.0, "savedBy": null, "track": "s", "numFloors": 5, "difficulty": 6, "state": "suit", "block": 26}, "38": {"becameSuitTime": 1482194333.432, "savedBy": null, "track": "c", "numFloors": 4, "difficulty": 4, "state": "suit", "block": 38}, "28": {"becameSuitTime": 1482194158.327, "savedBy": null, "track": "g", "numFloors": 4, "difficulty": 5, "state": "suit", "block": 28}, "37": {"becameSuitTime": 1482194294.349, "savedBy": null, "track": "l", "numFloors": 4, "difficulty": 5, "state": "suit", "block": 37}}