{"2": {"becameSuitTime": 1482194201.377, "savedBy": null, "track": "l", "numFloors": 1, "difficulty": 2, "state": "suit", "block": 2}, "6": {"becameSuitTime": 1482194008.01, "savedBy": null, "track": "g", "numFloors": 2, "difficulty": 2, "state": "suit", "block": 6}, "10": {"becameSuitTime": 1482194257.051, "savedBy": null, "track": "l", "numFloors": 4, "difficulty": 5, "state": "suit", "block": 10}, "11": {"becameSuitTime": 1482194080.448, "savedBy": null, "track": "c", "numFloors": 4, "difficulty": 5, "state": "suit", "block": 11}, "13": {"becameSuitTime": 1482194132.432, "savedBy": null, "track": "g", "numFloors": 3, "difficulty": 3, "state": "suit", "block": 13}, "20": {"becameSuitTime": 1482194191.765, "savedBy": null, "track": "c", "numFloors": 2, "difficulty": 4, "state": "suit", "block": 20}, "30": {"becameSuitTime": 1482193941.006, "savedBy": null, "track": "c", "numFloors": 4, "difficulty": 4, "state": "suit", "block": 30}}