{"7": {"becameSuitTime": 1482428655.95, "savedBy": null, "track": "g", "numFloors": 2, "difficulty": 4, "state": "suit", "block": 7}, "17": {"becameSuitTime": 1482391687.765, "savedBy": null, "track": "m", "numFloors": 2, "difficulty": 3, "state": "suit", "block": 17}, "18": {"becameSuitTime": 1482391586.986, "savedBy": null, "track": "m", "numFloors": 1, "difficulty": 1, "state": "suit", "block": 18}, "20": {"becameSuitTime": 1482391440.346, "savedBy": null, "track": "m", "numFloors": 1, "difficulty": 1, "state": "suit", "block": 20}, "25": {"becameSuitTime": 1482400122.564, "savedBy": null, "track": "s", "numFloors": 1, "difficulty": 2, "state": "suit", "block": 25}, "28": {"becameSuitTime": 1482427454.676, "savedBy": null, "track": "m", "numFloors": 1, "difficulty": 1, "state": "suit", "block": 28}}