{"1": {"becameSuitTime": 1482277066.833, "savedBy": null, "track": "l", "numFloors": 4, "difficulty": 5, "state": "suit", "block": 1}, "67": {"becameSuitTime": 1482276980.9, "savedBy": null, "track": "g", "numFloors": 5, "difficulty": 7, "state": "suit", "block": 67}, "3": {"becameSuitTime": 1482276819.089, "savedBy": null, "track": "g", "numFloors": 4, "difficulty": 4, "state": "suit", "block": 3}, "68": {"becameSuitTime": 1482277002.117, "savedBy": null, "track": "g", "numFloors": 2, "difficulty": 4, "state": "suit", "block": 68}, "41": {"becameSuitTime": 1482277509.705, "savedBy": null, "track": "g", "numFloors": 3, "difficulty": 6, "state": "suit", "block": 41}, "48": {"becameSuitTime": 1482277056.198, "savedBy": null, "track": "g", "numFloors": 3, "difficulty": 5, "state": "suit", "block": 48}, "35": {"becameSuitTime": 1482276994.071, "savedBy": null, "track": "g", "numFloors": 2, "difficulty": 4, "state": "suit", "block": 35}, "52": {"becameSuitTime": 1482276912.694, "savedBy": null, "track": "g", "numFloors": 3, "difficulty": 5, "state": "suit", "block": 52}, "55": {"becameSuitTime": 1482276938.224, "savedBy": null, "track": "g", "numFloors": 5, "difficulty": 6, "state": "suit", "block": 55}, "28": {"becameSuitTime": 1482276673.746, "savedBy": null, "track": "g", "numFloors": 3, "difficulty": 4, "state": "suit", "block": 28}, "29": {"becameSuitTime": 1482276464.266, "savedBy": null, "track": "c", "numFloors": 5, "difficulty": 6, "state": "suit", "block": 29}}