{"32": {"becameSuitTime": 1482340327.984, "savedBy": null, "track": "g", "numFloors": 3, "difficulty": 2, "state": "suit", "block": 32}, "33": {"becameSuitTime": 1482344414.487, "savedBy": null, "track": "c", "numFloors": 3, "difficulty": 4, "state": "suit", "block": 33}, "7": {"becameSuitTime": 1482339971.215, "savedBy": null, "track": "c", "numFloors": 3, "difficulty": 5, "state": "suit", "block": 7}, "10": {"becameSuitTime": 1482340701.32, "savedBy": null, "track": "c", "numFloors": 3, "difficulty": 3, "state": "suit", "block": 10}, "21": {"becameSuitTime": 1482341996.718, "savedBy": null, "track": "l", "numFloors": 4, "difficulty": 4, "state": "suit", "block": 21}, "25": {"becameSuitTime": 1482340306.1, "savedBy": null, "track": "g", "numFloors": 2, "difficulty": 2, "state": "suit", "block": 25}, "26": {"becameSuitTime": 1482340512.464, "savedBy": null, "track": "c", "numFloors": 2, "difficulty": 2, "state": "suit", "block": 26}}